conformer/__init__.py
conformer/conformer.py
conformer-0.3.2.dist-info/LICENSE
conformer-0.3.2.dist-info/METADATA
conformer-0.3.2.dist-info/WHEEL
conformer-0.3.2.dist-info/top_level.txt
conformer-0.3.2.dist-info/RECORD
