Metadata-Version: 2.1
Name: conformer
Version: 0.3.2
Summary: The convolutional module from the Conformer paper
Home-page: https://github.com/lucidrains/conformer
Author: Phil Wang
Author-email: lucidrains@gmail.com
License: MIT
Keywords: artificial intelligence,deep learning,transformers,audio
Classifier: Development Status :: 4 - Beta
Classifier: Intended Audience :: Developers
Classifier: Topic :: Scientific/Engineering :: Artificial Intelligence
Classifier: License :: OSI Approved :: MIT License
Classifier: Programming Language :: Python :: 3.6
License-File: LICENSE
Requires-Dist: einops (>=0.6.1)
Requires-Dist: torch
